CHANGES.rst
CONTRIBUTORS.rst
LICENSE
MANIFEST.in
README.rst
setup.py
docs/Makefile
docs/__init__.py
docs/__init__.pyc
docs/conf.py
docs/index.rst
docs/make.bat
docs/requirements.txt
docs/api/edeposit.amqp.serializers.serializers.rst
docs/api/modules.rst
src/edeposit/__init__.py
src/edeposit.amqp.serializers.egg-info/PKG-INFO
src/edeposit.amqp.serializers.egg-info/SOURCES.txt
src/edeposit.amqp.serializers.egg-info/dependency_links.txt
src/edeposit.amqp.serializers.egg-info/namespace_packages.txt
src/edeposit.amqp.serializers.egg-info/not-zip-safe
src/edeposit.amqp.serializers.egg-info/requires.txt
src/edeposit.amqp.serializers.egg-info/top_level.txt
src/edeposit/amqp/__init__.py
src/edeposit/amqp/serializers/__init__.py
src/edeposit/amqp/serializers/serializers.py
src/edeposit/amqp/serializers/tests/inspector.py
src/edeposit/amqp/serializers/tests/test_namedtuple_serializer.txt
src/edeposit/amqp/serializers/tests/test_package.txt