Metadata-Version: 1.1
Name: edeposit.amqp.serializers
Version: 1.2.0
Summary: E-Deposit's AMQP definitions and common classes/patterns.
Home-page: https://github.com/edeposit/edeposit.amqp.serializers/
Author: Edeposit team
Author-email: edeposit@email.cz
License: GPL2+
Platform: UNKNOWN
Classifier: Programming Language :: Python :: 2.7
Classifier: License :: OSI Approved :: GNU General Public License v2 or later (GPLv2+)
Classifier: Topic :: Software Development :: Libraries :: Python Modules
